PY3021/__init__.py
PY3021/pdf.py
PY3021/tools.py
SUN_01/CFPDF.py
SUN_01/HBPDF.py
SUN_01/__init__.py
SUN_01-1.1.dist-info/METADATA
SUN_01-1.1.dist-info/WHEEL
SUN_01-1.1.dist-info/top_level.txt
SUN_01-1.1.dist-info/RECORD
