Metadata-Version: 2.1
Name: SUN-01
Version: 1.1
Summary: UNKNOWN
Home-page: https://xxx.com
Author: PY3021
Author-email: 111@qq.com
License: UNKNOWN
Platform: UNKNOWN
Requires-Python: >=3.6
Requires-Dist: requests (>=2.25.0)
Requires-Dist: lxml
Requires-Dist: pikepdf
Requires-Dist: tkinter
Requires-Dist: PIL
Requires-Dist: ttkbootstrap
